{
  "sessionName": "Session_2025-07-08T23:49:09.903Z",
  "createdAt": "2025-07-08T23:49:09.903Z",
  "liveWorkspace": {
    "apps": [],
    "activeAppId": null,
    "activeWindowId": null
  },
  "eventLog": [
    {
      "type": "session_started",
      "timestamp": "2025-07-08T23:49:09.903Z",
      "data": {
        "type": "session_started",
        "sessionName": "Session_2025-07-08T23:49:09.903Z"
      }
    },
    {
      "type": "poll_snapshot",
      "timestamp": "2025-07-08T23:49:13.124Z",
      "appName": "Electron",
      "windowTitle": "Cortex"
    },
    {
      "type": "poll_snapshot",
      "timestamp": "2025-07-08T23:49:16.066Z",
      "appName": "Electron",
      "windowTitle": "Cortex"
    },
    {
      "type": "poll_snapshot",
      "timestamp": "2025-07-08T23:49:19.075Z",
      "appName": "Electron",
      "windowTitle": "Cortex"
    },
    {
      "type": "poll_snapshot",
      "timestamp": "2025-07-08T23:49:22.101Z",
      "appName": "Electron",
      "windowTitle": "Cortex"
    },
    {
      "type": "poll_snapshot",
      "timestamp": "2025-07-08T23:49:25.067Z",
      "appName": "Electron",
      "windowTitle": "Cortex"
    },
    {
      "type": "poll_snapshot",
      "timestamp": "2025-07-08T23:49:28.073Z",
      "appName": "Electron",
      "windowTitle": "Cortex"
    },
    {
      "type": "poll_snapshot",
      "timestamp": "2025-07-08T23:49:31.073Z",
      "appName": "Visual Studio Code",
      "windowTitle": "package.json — cortex"
    },
    {
      "type": "poll_snapshot",
      "timestamp": "2025-07-08T23:49:34.093Z",
      "appName": "Visual Studio Code",
      "windowTitle": "package.json — cortex"
    },
    {
      "type": "poll_snapshot",
      "timestamp": "2025-07-08T23:49:37.084Z",
      "appName": "Visual Studio Code",
      "windowTitle": "package.json — cortex"
    },
    {
      "type": "poll_snapshot",
      "timestamp": "2025-07-08T23:49:40.096Z",
      "appName": "Visual Studio Code",
      "windowTitle": "index.css — cortex"
    },
    {
      "type": "poll_snapshot",
      "timestamp": "2025-07-08T23:49:43.129Z",
      "appName": "Visual Studio Code",
      "windowTitle": "index.css — cortex"
    },
    {
      "type": "poll_snapshot",
      "timestamp": "2025-07-08T23:49:46.108Z",
      "appName": "Visual Studio Code",
      "windowTitle": "index.css — cortex"
    },
    {
      "type": "poll_snapshot",
      "timestamp": "2025-07-08T23:49:49.107Z",
      "appName": "Visual Studio Code",
      "windowTitle": "index.css — cortex"
    },
    {
      "type": "poll_snapshot",
      "timestamp": "2025-07-08T23:49:52.139Z",
      "appName": "Visual Studio Code",
      "windowTitle": "index.css — cortex"
    },
    {
      "type": "poll_snapshot",
      "timestamp": "2025-07-08T23:49:55.101Z",
      "appName": "Visual Studio Code",
      "windowTitle": "index.css — cortex"
    },
    {
      "type": "poll_snapshot",
      "timestamp": "2025-07-08T23:49:58.131Z",
      "appName": "Visual Studio Code",
      "windowTitle": "SpatialNavigator.tsx — cortex"
    },
    {
      "type": "poll_snapshot",
      "timestamp": "2025-07-08T23:50:01.123Z",
      "appName": "Visual Studio Code",
      "windowTitle": "SpatialNavigator.tsx — cortex"
    },
    {
      "type": "poll_snapshot",
      "timestamp": "2025-07-08T23:50:04.157Z",
      "appName": "Visual Studio Code",
      "windowTitle": "SpatialNavigator.tsx — cortex"
    },
    {
      "type": "poll_snapshot",
      "timestamp": "2025-07-08T23:50:07.172Z",
      "appName": "Visual Studio Code",
      "windowTitle": "SpatialNavigator.tsx — cortex"
    },
    {
      "type": "poll_snapshot",
      "timestamp": "2025-07-08T23:50:10.161Z",
      "appName": "Visual Studio Code",
      "windowTitle": "SpatialNavigator.tsx — cortex"
    },
    {
      "type": "poll_snapshot",
      "timestamp": "2025-07-08T23:50:13.174Z",
      "appName": "Visual Studio Code",
      "windowTitle": "SpatialNavigator.tsx — cortex"
    },
    {
      "type": "poll_snapshot",
      "timestamp": "2025-07-08T23:50:16.202Z",
      "appName": "Visual Studio Code",
      "windowTitle": "SpatialNavigator.tsx — cortex"
    },
    {
      "type": "poll_snapshot",
      "timestamp": "2025-07-08T23:50:19.174Z",
      "appName": "Visual Studio Code",
      "windowTitle": "index.css — cortex"
    },
    {
      "type": "poll_snapshot",
      "timestamp": "2025-07-08T23:50:22.184Z",
      "appName": "Visual Studio Code",
      "windowTitle": "index.css — cortex"
    },
    {
      "type": "poll_snapshot",
      "timestamp": "2025-07-08T23:50:25.165Z",
      "appName": "Visual Studio Code",
      "windowTitle": "index.css — cortex"
    },
    {
      "type": "poll_snapshot",
      "timestamp": "2025-07-08T23:50:28.170Z",
      "appName": "Visual Studio Code",
      "windowTitle": "index.css — cortex"
    },
    {
      "type": "poll_snapshot",
      "timestamp": "2025-07-08T23:50:31.157Z",
      "appName": "Visual Studio Code",
      "windowTitle": "index.css — cortex"
    },
    {
      "type": "poll_snapshot",
      "timestamp": "2025-07-08T23:50:34.165Z",
      "appName": "Visual Studio Code",
      "windowTitle": "tailwind.config.ts — cortex"
    },
    {
      "type": "poll_snapshot",
      "timestamp": "2025-07-08T23:50:37.184Z",
      "appName": "Visual Studio Code",
      "windowTitle": "tailwind.config.ts — cortex"
    },
    {
      "type": "poll_snapshot",
      "timestamp": "2025-07-08T23:50:40.198Z",
      "appName": "Visual Studio Code",
      "windowTitle": "tailwind.config.ts — cortex"
    },
    {
      "type": "poll_snapshot",
      "timestamp": "2025-07-08T23:50:43.191Z",
      "appName": "Visual Studio Code",
      "windowTitle": "tailwind.config.ts — cortex"
    },
    {
      "type": "poll_snapshot",
      "timestamp": "2025-07-08T23:50:46.201Z",
      "appName": "Visual Studio Code",
      "windowTitle": "tailwind.config.ts — cortex"
    },
    {
      "type": "poll_snapshot",
      "timestamp": "2025-07-08T23:50:49.210Z",
      "appName": "Visual Studio Code",
      "windowTitle": "tailwind.config.ts — cortex"
    },
    {
      "type": "poll_snapshot",
      "timestamp": "2025-07-08T23:50:52.219Z",
      "appName": "Visual Studio Code",
      "windowTitle": "tailwind.config.ts — cortex"
    },
    {
      "type": "poll_snapshot",
      "timestamp": "2025-07-08T23:50:55.198Z",
      "appName": "Visual Studio Code",
      "windowTitle": "tailwind.config.ts — cortex"
    },
    {
      "type": "tab_focus",
      "timestamp": "2025-07-08T23:50:58.323Z",
      "appName": "Google Chrome",
      "windowTitle": "Tailwind CSS Breakdown"
    },
    {
      "type": "session_paused",
      "timestamp": "2025-07-08T23:51:00.963Z",
      "data": {
        "type": "session_paused"
      }
    },
    {
      "type": "session_paused",
      "timestamp": "2025-07-08T23:51:00.964Z",
      "data": {
        "type": "session_paused"
      }
    }
  ]
}